README.rst
setup.cfg
setup.py
./__init__.py
./carrier.py
./configuration.py
./configuration.xml
./party.py
./sale.py
./sale.xml
./shipment_box_type.xml
./shipping_data.xml
./stock.py
./stock.xml
./tryton.cfg
./locale/de_DE.po
./tests/__init__.py
./tests/test_ups.py
./view/carrier_form.xml
./view/sale_configuration_view_form.xml
./view/shipping_ups_configuration_form.xml
./view/ups_configuration_form.xml
fio_shipping_ups.egg-info/PKG-INFO
fio_shipping_ups.egg-info/SOURCES.txt
fio_shipping_ups.egg-info/dependency_links.txt
fio_shipping_ups.egg-info/entry_points.txt
fio_shipping_ups.egg-info/not-zip-safe
fio_shipping_ups.egg-info/requires.txt
fio_shipping_ups.egg-info/top_level.txt